Tugas 2/ALUControl.v
/* Modul ALUControl menentukan sinyal kontrol untuk ALU berdasarkan nilai ALUOp dan FuncCode.
   Modul ini biasanya digunakan dalam datapath arsitektur prosesor MIPS untuk instruksi R-type dan lainnya */
module ALUControl (ALUOp, FuncCode, ALUCtl);

    // ALUOp adalah sinyal kontrol 2-bit dari unit kontrol utama yang menunjukkan jenis operasi
    input [1:0] ALUOp;

    // FuncCode adalah kode fungsi dari field "funct" pada instruksi R-type (6-bit)
    input [5:0] FuncCode;

    /* ALUCtl adalah sinyal kontrol output ke ALU untuk menentukan operasi apa yang akan dilakukan.
       Output 4-bit ini bisa bernilai kode seperti 0000 (AND), 0010 (ADD), 0110 (SUB), dsb. */
    output reg [3:0] ALUCtl;

    // Blok always akan mengevaluasi ulang ketika nilai ALUOp atau FuncCode berubah
    always @(ALUOp, FuncCode) begin

        /* Jika ALUOp = 00 => instruksi adalah LW atau SW, maka
           ALU harus melakukan penjumlahan (untuk menghitung alamat: base + offset) */
        if(ALUOp == 2'b00)
            ALUCtl <= 4'b0010;  // Kode 2: ADD

        /* Jika ALUOp = 01 => instruksi adalah BEQ, maka
           ALU harus melakukan pengurangan untuk membandingkan apakah dua register sama */
        else if(ALUOp == 2'b01)
            ALUCtl <= 4'b0110;  // Kode 6: SUB

        /* Jika ALUOp = 10 => instruksi adalah R-type,
           maka operasi ditentukan oleh field funct (FuncCode) */
        else begin
            case(FuncCode)
                6'd32: ALUCtl <= 4'b0010; // ADD  (funct = 32) => kode ALU 2
                6'd34: ALUCtl <= 4'b0110; // SUB  (funct = 34) => kode ALU 6
                6'd36: ALUCtl <= 4'b0000; // AND  (funct = 36) => kode ALU 0
                6'd37: ALUCtl <= 4'b0001; // OR   (funct = 37) => kode ALU 1
                6'd39: ALUCtl <= 4'b1100; // NOR  (funct = 39) => kode ALU 12
                6'd42: ALUCtl <= 4'b0111; // SLT  (funct = 42) => kode ALU 7
                default: ALUCtl <= 4'b1111; // nilai default jika FuncCode tidak dikenali (error)
            endcase
        end
    end

endmodule

Tugas 2/Mux3.v
// Modul bernama Mux3 adalah modul multiplexer 2 ke 1 dengan lebar data 32-bit
module Mux3 (
    ReadData,    // Input data dari memori (biasanya hasil pembacaan dari data memory)
    ALUOut,      // Input data dari ALU (hasil operasi aritmatika / logika)
    MemtoReg,    // Sinyal kontrol untuk memilih antara ReadData atau ALUOut
    WriteData    // Output yang akan ditulis ke register
);

// Input 32-bit : ReadData dari memory dan ALUOut dari ALU
input [31:0] ReadData, ALUOut;

// Input kontrol 1-bit : MemtoReg menentukan sumber data yang dipilih
input MemtoReg;

// Output 32-bit bertipe reg : WriteData adalah data akhir yang akan ditulis ke register file
output reg [31:0] WriteData;

// Blok always dengan sensitivitas terhadap semua sinyal (* berarti semua input dipantau)
// Digunakan untuk mendeskripsikan perilaku multiplexer secara combinational (tanpa clock)
always @(*) begin
    // Pemilihan nilai WriteData berdasarkan nilai MemtoReg
    case (MemtoReg)
        0: WriteData <= ALUOut;    // Jika MemtoReg = 0, pilih output dari ALU
        1: WriteData <= ReadData;  // Jika MemtoReg = 1, pilih output dari memory (ReadData)
    endcase
end

endmodule

Tugas 2/MainControl.v
/* Modul Main Control berfungsi untuk menghasilkan sinyal kontrol utama untuk prosesor,
berdasarkan nilai Opcode dari instruksi yang sedang dijalankan. */
module MainControl(
	input [5:0] Opcode, // Input 6-bit Opcode dari instruksi
	
	// Output sinyal kontrol yang akan digunakan oleh komponen lain
	output reg RegDst, RegWrite, ALUSrc,
	output reg MemtoReg, MemRead, MemWrite,
	output reg Branch,
	output reg [1:0] ALUOp // Output 2-bit ALUOp yang akan digunakan oleh ALU Control
);

	/* Blok always dengan sensitivitas ke semua sinyal (*),
	berarti blok ini akan dieksekusi ulang setiap kali ada perubahan nilai sinyal input. */
	always @(*) begin
		// Pemilihan sinyal kontrol berdasarkan nilai Opcode
		case(Opcode)
			// R-type instruction (Opcode = 0)
			0: begin
				RegDst 		<= 1;		// Tujuan register ditentukan oleh field rd
				ALUSrc 		<= 0;		// Operan kedua ALU berasal dari register, bukan immediate
				MemtoReg	<= 0;		// Data yang ditulis ke register berasal dari ALU, bukan dari memory
				RegWrite	<= 1;		// Aktifkan penulisan ke register
				MemRead		<= 0;		// Tidak membaca dari memory
				MemWrite	<= 0;		// Tidak menulis ke memory
				Branch		<= 0;		// Bukan instruksi branch
				ALUOp		<= 2'b10;	// Kode ALU untuk R-type (akan dikontrol oleh funct)
			end
			
			// LW (Load Word, Opcode = 35)
			35: begin
				RegDst 		<= 0;		// Tujuan register adalah rt
				ALUSrc 		<= 1;		// Operan kedua ALU berasal dari immediate
				MemtoReg	<= 1;		// Data yang ditulis ke register berasal dari memory
				RegWrite	<= 1;		// Aktifkan penulisan ke register
				MemRead		<= 1;		// Aktifkan pembacaan dari memory
				MemWrite	<= 0;		// Tidak menulis ke memory
				Branch		<= 0;		// Bukan instruksi branch
				ALUOp		<= 2'b00;	// Kode ALU untuk operasi penjumlahan (digunakan untuk address calculation)
			end

			// SW (Store Word, Opcode = 43)
			43: begin
				RegDst 		<= 0;		// Tidak digunakan
				ALUSrc 		<= 1;		// Operan kedua ALU berasal dari immediate
				MemtoReg	<= 0;		// Tidak digunakan
				RegWrite	<= 0;		// Tidak menulis ke register
				MemRead		<= 0;		// Tidak membaca dari memory
				MemWrite	<= 1;		// Aktifkan penulisan ke memory
				Branch		<= 0;		// Bukan instruksi branch
				ALUOp		<= 2'b00;	// Kode ALU untuk penjumlahan (digunakan untuk address calculation)
			end

			// BEQ (Branch if Equal, Opcode = 4)
			4: begin
				RegDst 		<= 0;		// Tidak digunakan
				ALUSrc 		<= 0;		// Operan kedua ALU berasal dari register
				MemtoReg	<= 0;		// Tidak digunakan
				RegWrite	<= 0;		// Tidak menulis ke register
				MemRead		<= 0;		// Tidak membaca dari memory
				MemWrite	<= 0;		// Tidak menulis ke memory
				Branch		<= 1;		// Aktifkan branching
				ALUOp		<= 2'b01;	// Kode ALU untuk operasi pengurangan (digunakan untuk membandingkan kesamaan)
			end
		endcase
	end
endmodule

Tugas 2/DataMemory.v
/* Modul Data Memory digunakan untuk menyimulasikan memori data dalam arsitektur prosesor.
 Modul ini mendukung operasi baca (read) dan tulis (write) data ke/dari memory. */
module DataMemory (clock, address, MemWrite, MemRead, WriteData, ReadData);

    // Deklarasi input
    input clock;                     // Sinyal clock sebagai pemicu operasi baca/tulis
    input [6:0] address;             // Alamat 7-bit (128 lokasi memory)
    input MemWrite, MemRead;         // Sinyal kontrol untuk operasi tulis dan baca
    input [31:0] WriteData;          // Data 32-bit yang akan ditulis ke memori
    
    // Deklarasi output
    output reg [31:0] ReadData;      // Data 32-bit hasil pembacaan dari memory

    // Deklarasi memory 128 entri, masing-masing 32 bit
    reg [31:0] Mem[0:127]; // 32-bit memory array sebanyak 128 slot

    // Blok inisialisasi awal
    initial begin
        Mem[0] = 0; // Inisialisasi alamat memori ke-0 dengan nilai 0
    end

    // Blok tulis ke memory yang dipicu oleh **sisi naik (posedge)** dari clock
    always @ (posedge clock) begin
        if (MemWrite == 1)                     // Jika sinyal MemWrite aktif
            Mem[address[6:2]] <= WriteData;    // Tulis WriteData ke alamat tertentu
                                               // address[6:2] digunakan agar word-aligned (4-byte aligned)
    end

    // Blok baca dari memory yang dipicu oleh **sisi turun (negedge)** dari clock
    always @(negedge clock) begin
        if (MemRead == 1)                      // Jika sinyal MemRead aktif
            ReadData <= Mem[address[6:2]];     // Baca data dari memory ke ReadData
    end    

endmodule

Tugas 2/ALU.v
/* Modul ALU : Arithmetic Logic Unit 32-bit yang
   menerima dua input data 32-bit dan satu sinyal kontrol ALU untuk menentukan operasi */
module ALU (
    ALUCtl,   // Sinyal kontrol 4-bit yang menentukan jenis operasi ALU
    A,        // Operand pertama (input 32-bit)
    B,        // Operand kedua (input 32-bit)
    ALUOut,   // Output hasil operasi ALU
    Zero      // Output 1-bit, bernilai 1 jika hasil ALU adalah nol
);

// -------------------- [ INPUT ] ----------------------

// Input sinyal kontrol ALU 4-bit: menentukan operasi logika/arithmetic
input [3:0] ALUCtl;

// Dua input 32-bit: biasanya data dari register file
input [31:0] A, B;

// -------------------- [ OUTPUT ] ----------------------

// Output hasil ALU bertipe reg 32-bit
output reg [31:0] ALUOut;

// Output sinyal Zero: bernilai 1 jika hasil operasi ALU adalah nol
output Zero;

/* Penugasan langsung (combinational assignment) untuk sinyal Zero
   Jika hasil ALU (ALUOut) adalah nol, maka Zero = 1, sebaliknya Zero = 0 */
assign Zero = (ALUOut == 0);

// -------------------- [ LOGIKA OPERASI ALU ] ----------------------

/* Blok always dijalankan saat terjadi perubahan pada ALUCtl, A, atau B
   Menentukan hasil ALUOut berdasarkan sinyal kontrol ALUCtl */
always @(ALUCtl, A, B) begin
    case (ALUCtl)
        4'b0000: ALUOut <= A & B;             // Operasi AND bitwise
        4'b0001: ALUOut <= A | B;             // Operasi OR bitwise
        4'b0010: ALUOut <= A + B;             // Penjumlahan (ADD)
        4'b0110: ALUOut <= A - B;             // Pengurangan (SUB)
        4'b0111: ALUOut <= (A < B) ? 1 : 0;   // Operasi Set on Less Than (SLT): jika A < B, hasil 1, else 0
        4'b1100: ALUOut <= ~(A | B);          // Operasi NOR bitwise (negasi dari OR)
        
        // Default: jika ALUCtl tidak dikenali, maka hasilkan 0
        default: ALUOut <= 0;
    endcase
end

endmodule

Tugas 2/RegisterFile.v
// Modul RegFile adalah implementasi 32 general-purpose register (32-bit) Register File seperti pada arsitektur prosesor MIPS
module RegFile(
    input clock,                 // Sinyal clock untuk sinkronisasi penulisan data
    input RegWrite,              // Sinyal kontrol: aktif (1) jika ingin menulis ke register
    input [4:0] ReadReg1,        // Alamat register pertama untuk dibaca (5-bit = 32 register)
    input [4:0] ReadReg2,        // Alamat register kedua untuk dibaca
    input [4:0] WriteReg,        // Alamat register tujuan penulisan data
    input [31:0] WriteData,      // Data yang akan ditulis ke register
    output [31:0] ReadData1,     // Data hasil pembacaan dari ReadReg1
    output [31:0] ReadData2      // Data hasil pembacaan dari ReadReg2
);

    // Deklarasi array reg 32 elemen, masing-masing 32-bit yang merepresentasikan 32 register
    reg [31:0] reg_mem [0:31];

    /* Inisialisasi awal : register ke-0 di-set ke 0 sesuai konvensi MIPS 
    Register 0 bersifat konstan dan tidak boleh berubah */
    initial reg_mem[0] = 0;

    /* Blok pembacaan register : asynchronous (tidak tergantung clock)
       Jika register yang dibaca adalah R0 (index 0), maka hasil pembacaannya selalu 0.
       Selain itu, data diambil langsung dari array reg_mem */
    assign ReadData1 = (ReadReg1 == 0) ? 0 : reg_mem[ReadReg1];
    assign ReadData2 = (ReadReg2 == 0) ? 0 : reg_mem[ReadReg2];

    /* Blok penulisan register : synchronous (bergantung pada clock)
       Penulisan hanya terjadi saat sinyal RegWrite aktif (1)
       dan alamat register tujuan bukan R0 (WriteReg != 0),
       untuk menjaga agar register 0 tetap tidak bisa ditulis */
    always @(posedge clock) begin
        if(RegWrite && (WriteReg != 0)) begin
            reg_mem[WriteReg] <= WriteData;  // Menulis data ke register tujuan
        end
    end

endmodule

Tugas 2/Mux2.v
// Modul Mux2 adalah modul Multiplexer 2 input yang memilih antara ReadData2 dan Extend32
module Mux2(
    // Mendeklarasikan input ALUSrc, ReadData2, dan Extend32 serta output ALU_B
    input ALUSrc,                // Sinyal kontrol untuk memilih input ke ALU_B
    input [31:0] ReadData2,      // Input pertama dari register file (biasanya operand kedua)
    input [31:0] Extend32,       // Input kedua hasil sign-extend immediate
    output reg [31:0] ALU_B      // Output yang akan digunakan sebagai input kedua ALU
);

    // Mendeklarasikan always block yang sensitif terhadap perubahan sinyal apa pun (*)
    always @(*) begin
        // Gunakan case untuk memilih input berdasarkan nilai ALUSrc
        case(ALUSrc)
            0: ALU_B = ReadData2;  // Jika ALUSrc = 0, gunakan data dari register (ReadData2)
            1: ALU_B = Extend32;   // Jika ALUSrc = 1, gunakan immediate yang sudah diperluas (Extend32)
        endcase
    end

endmodule

Tugas 2/testbench.v
// Include semua modul eksternal yang dibutuhkan dalam simulasi
`include "ALU.v"
`include "DataMemory.v"
`include "MainControl.v"
`include "RegisterFile.v"
`include "Mux2.v"
`include "Mux3.v"
`include "ALUControl.v"

// Definisikan time scale untuk simulasi: 1 ns step dan 1 ps precision
`timescale 1ns / 1ps

module testbench;
    // -------------------- [ DEFINISI INPUT UNTUK MODUL ] --------------------
    reg clock;
    reg [5:0] Opcode;               // Opcode untuk menentukan jenis instruksi
    reg [3:0] ALUCtl;               // Sinyal kontrol ALU
    reg [4:0] ReadReg1, ReadReg2;   // Register sumber
    reg [4:0] WriteReg;             // Register tujuan
    reg [31:0] Immediate;           // Nilai immediate untuk instruksi I-type
    
    // -------------------- [ OUTPUT YANG AKAN DIPANTAU ] ---------------------
    wire [31:0] ReadData1, ReadData2; // Nilai dari register file
    wire [31:0] ALUOut;               // Output dari ALU
    wire Zero;                        // Flag hasil ALU = 0
    reg RegWrite;                     // Sinyal write ke register
    wire [31:0] WriteData;            // Data yang akan ditulis ke register
    
    // -------------------- [ SIGNAL UNTUK DATA MEMORY ] ----------------------
    reg MemWrite_data;
    reg MemRead_data;
    reg [6:0] address_data;           // Alamat memori
    wire [31:0] ReadData_data;        // Data yang dibaca dari memori

    // -------------------- [ MUX UNTUK PEMILIH B_INPUT ] ---------------------
    // Jika ALUSrc = 1 (immediate mode), maka input B dari ALU adalah Immediate
    wire [31:0] B_input;
    Mux2 mux_imm(
        .ALUSrc(Opcode[5]),       // Bit 5 dari opcode digunakan untuk kontrol ALUSrc
        .ReadData2(ReadData2),    // Input dari register
        .Extend32(Immediate),     // Nilai immediate
        .ALU_B(B_input)           // Output ke input B ALU
    );

    // -------------------- [ MENGHUBUNGKAN ALU KE REGISTER FILE ] -----------
    assign WriteData = ALUOut; // Hasil ALU akan ditulis ke register file

    // -------------------- [ INSTANSIASI MODUL REGISTER FILE ] --------------
    RegFile reg_file(
        .clock(clock),
        .RegWrite(RegWrite),
        .ReadReg1(ReadReg1),
        .ReadReg2(ReadReg2),
        .WriteReg(WriteReg),
        .WriteData(WriteData),
        .ReadData1(ReadData1),
        .ReadData2(ReadData2)
    );

    // -------------------- [ INSTANSIASI MODUL ALU ] ------------------------
    ALU alu(
        .ALUCtl(ALUCtl),
        .A(ReadData1), // Operand A dari register file
        .B(B_input),   // Operand B dari Mux2 (ReadData2 atau Immediate)
        .ALUOut(ALUOut),
        .Zero(Zero)
    );

    // -------------------- [ INSTANSIASI MODUL DATA MEMORY ] ----------------
    DataMemory data_mem(
        .clock(clock),
        .address(address_data),
        .MemWrite(MemWrite_data),
        .MemRead(MemRead_data),
        .WriteData(WriteData),
        .ReadData(ReadData_data)
    );

    // -------------------- [ GENERATOR CLOCK (frekuensi 100MHz) ] -----------
    always #5 clock = ~clock; // Clock toggle setiap 5ns => periode 10ns

    // -------------------- [ PROSES SIMULASI ] ------------------------------
    initial begin
        // Inisialisasi clock dan file output
        clock = 0;
        $dumpfile("testbench.vcd");      // File output untuk waveform
        $dumpvars(0, testbench);         // Simpan semua sinyal untuk pemantauan

        // Inisialisasi sinyal kontrol
        RegWrite = 1;                    // Aktifkan write ke register
        ALUCtl = 4'b0010;                // Operasi ADD
        Opcode = 6'b100000;             // Immediate mode (bit ke-5 = 1)

        $display("\n=== Simulasi Dimulai ===");
        $display("Time(ns)\tOperation\t\tResult");
        $display("-----------------------------------------");

        // -------------------- [ SIMULASI LOAD IMMEDIATE KE REGISTER ] -------
        // Instruksi "Load Immediate" (bukan instruksi MIPS asli) untuk mengisi register
        Immediate = 32'd5; 
        ReadReg1 = 0; ReadReg2 = 0; WriteReg = 1;
        #10; $display("%8t\tLI $1 = %0d", $time, reg_file.reg_mem[1]);

        Immediate = 32'd2; WriteReg = 2;
        #10; $display("%8t\tLI $2 = %0d", $time, reg_file.reg_mem[2]);

        Immediate = 32'd0; WriteReg = 3;
        #10; $display("%8t\tLI $3 = %0d", $time, reg_file.reg_mem[3]);

        Immediate = 32'd5; WriteReg = 4;
        #10; $display("%8t\tLI $4 = %0d", $time, reg_file.reg_mem[4]);

        Immediate = 32'd6; WriteReg = 5;
        #10; $display("%8t\tLI $5 = %0d", $time, reg_file.reg_mem[5]);

        Immediate = 32'd3; WriteReg = 6;
        #10; $display("%8t\tLI $6 = %0d\n", $time, reg_file.reg_mem[6]);

        // -------------------- [ PROSES PENJUMLAHAN (R-TYPE)] ----------------
        Opcode = 6'b000000; // R-type, bit ke-5 = 0 → gunakan ReadData2
        // ADD $1 + $2 → $7
        ReadReg1 = 1; ReadReg2 = 2; WriteReg = 7;
        #10 $display("%8t\tADD $1 + $2\t\t$7 = %0d", $time, ALUOut);

        // ADD $7 + $3 → $8
        ReadReg1 = 7; ReadReg2 = 3; WriteReg = 8;
        #10 $display("%8t\tADD $7 + $3\t\t$8 = %0d", $time, ALUOut);

        // ADD $8 + $4 → $9
        ReadReg1 = 8; ReadReg2 = 4; WriteReg = 9;
        #10 $display("%8t\tADD $8 + $4\t\t$9 = %0d", $time, ALUOut);

        // ADD $9 + $5 → $10
        ReadReg1 = 9; ReadReg2 = 5; WriteReg = 10;
        #10 $display("%8t\tADD $9 + $5\t\t$10 = %0d", $time, ALUOut);

        // ADD $10 + $6 → $31
        ReadReg1 = 10; ReadReg2 = 6; WriteReg = 31;
        #10 $display("%8t\tADD $10 + $6\t\t$31 = %0d\n", $time, ALUOut);

        // -------------------- [ SIMPAN NILAI AKHIR KE DATA MEMORY ] ---------
        MemWrite_data = 1;             // Aktifkan penulisan ke memori
        address_data = 0;              // Tulis ke alamat memori 0

        ReadReg1 = 31;                 // Ambil data dari $31
        ReadReg2 = 0; ALUCtl = 4'b0010; // ALU tetap dalam mode ADD (tidak penting di sini)
        #10;
        $display("%8t\tDataMemory[0] = %0d (Dari Register $31)", $time, data_mem.Mem[0]);
        $display("%8t\tRegister $31 = %0d", $time, data_mem.Mem[0]);

        // -------------------- [ AKHIR SIMULASI ] ----------------------------
        #10 $display("-----------------------------------------");
        $display("=== Simulasi Selesai ===");
        $finish;
    end
endmodule

Tugas 2/testbench.vcd
$date
	Fri Apr 11 01:04:41 2025
$end
$version
	Icarus Verilog
$end
$timescale
	1ps
$end
$scope module testbench $end
$var wire 32 ! WriteData [31:0] $end
$var wire 1 " Zero $end
$var wire 32 # ReadData_data [31:0] $end
$var wire 32 $ ReadData2 [31:0] $end
$var wire 32 % ReadData1 [31:0] $end
$var wire 32 & B_input [31:0] $end
$var wire 32 ' ALUOut [31:0] $end
$var reg 4 ( ALUCtl [3:0] $end
$var reg 32 ) Immediate [31:0] $end
$var reg 1 * MemRead_data $end
$var reg 1 + MemWrite_data $end
$var reg 6 , Opcode [5:0] $end
$var reg 5 - ReadReg1 [4:0] $end
$var reg 5 . ReadReg2 [4:0] $end
$var reg 1 / RegWrite $end
$var reg 5 0 WriteReg [4:0] $end
$var reg 7 1 address_data [6:0] $end
$var reg 1 2 clock $end
$scope module alu $end
$var wire 4 3 ALUCtl [3:0] $end
$var wire 1 " Zero $end
$var wire 32 4 B [31:0] $end
$var wire 32 5 A [31:0] $end
$var reg 32 6 ALUOut [31:0] $end
$upscope $end
$scope module data_mem $end
$var wire 1 * MemRead $end
$var wire 1 + MemWrite $end
$var wire 32 7 WriteData [31:0] $end
$var wire 7 8 address [6:0] $end
$var wire 1 2 clock $end
$var reg 32 9 ReadData [31:0] $end
$upscope $end
$scope module mux_imm $end
$var wire 1 : ALUSrc $end
$var wire 32 ; Extend32 [31:0] $end
$var wire 32 < ReadData2 [31:0] $end
$var reg 32 = ALU_B [31:0] $end
$upscope $end
$scope module reg_file $end
$var wire 5 > ReadReg1 [4:0] $end
$var wire 5 ? ReadReg2 [4:0] $end
$var wire 1 / RegWrite $end
$var wire 32 @ WriteData [31:0] $end
$var wire 5 A WriteReg [4:0] $end
$var wire 1 2 clock $end
$var wire 32 B ReadData2 [31:0] $end
$var wire 32 C ReadData1 [31:0] $end
$upscope $end
$upscope $end
$enddefinitions $end
$comment Show the parameter values. $end
$dumpall
$end
#0
$dumpvars
b0 C
b0 B
b1 A
b101 @
b0 ?
b0 >
b101 =
b0 <
b101 ;
1:
bx 9
bx 8
b101 7
b101 6
b0 5
b101 4
b10 3
02
bx 1
b1 0
1/
b0 .
b0 -
b100000 ,
x+
x*
b101 )
b10 (
b101 '
b101 &
b0 %
b0 $
bx #
0"
b101 !
$end
#5000
12
#10000
b10 !
b10 7
b10 @
b10 '
b10 6
b10 &
b10 4
b10 =
02
b10 0
b10 A
b10 )
b10 ;
#15000
12
#20000
1"
b0 !
b0 7
b0 @
b0 '
b0 6
b0 &
b0 4
b0 =
02
b11 0
b11 A
b0 )
b0 ;
#25000
12
#30000
0"
b101 !
b101 7
b101 @
b101 '
b101 6
b101 &
b101 4
b101 =
02
b100 0
b100 A
b101 )
b101 ;
#35000
12
#40000
b110 !
b110 7
b110 @
b110 '
b110 6
b110 &
b110 4
b110 =
02
b101 0
b101 A
b110 )
b110 ;
#45000
12
#50000
b11 !
b11 7
b11 @
b11 '
b11 6
b11 &
b11 4
b11 =
02
b110 0
b110 A
b11 )
b11 ;
#55000
12
#60000
b111 !
b111 7
b111 @
b111 '
b111 6
b10 &
b10 4
b10 =
b10 $
b10 <
b10 B
b101 %
b101 5
b101 C
0:
02
b111 0
b111 A
b10 .
b10 ?
b1 -
b1 >
b0 ,
#65000
12
#70000
b111 !
b111 7
b111 @
b111 '
b111 6
b0 &
b0 4
b0 =
b0 $
b0 <
b0 B
b111 %
b111 5
b111 C
02
b1000 0
b1000 A
b11 .
b11 ?
b111 -
b111 >
#75000
12
#80000
b1100 !
b1100 7
b1100 @
b1100 '
b1100 6
b101 &
b101 4
b101 =
b101 $
b101 <
b101 B
02
b1001 0
b1001 A
b100 .
b100 ?
b1000 -
b1000 >
#85000
12
#90000
b10010 !
b10010 7
b10010 @
b10010 '
b10010 6
b110 &
b110 4
b110 =
b110 $
b110 <
b110 B
b1100 %
b1100 5
b1100 C
02
b1010 0
b1010 A
b101 .
b101 ?
b1001 -
b1001 >
#95000
12
#100000
b10101 !
b10101 7
b10101 @
b10101 '
b10101 6
b11 &
b11 4
b11 =
b11 $
b11 <
b11 B
b10010 %
b10010 5
b10010 C
02
b11111 0
b11111 A
b110 .
b110 ?
b1010 -
b1010 >
#105000
12
#110000
b10101 !
b10101 7
b10101 @
b10101 '
b10101 6
b0 &
b0 4
b0 =
b0 $
b0 <
b0 B
b10101 %
b10101 5
b10101 C
02
b0 .
b0 ?
b11111 -
b11111 >
b0 1
b0 8
1+
